base_str/__init__.py
base_str/base.py
fast_str/__init__.py
fast_str/fast.py
fast_string_geheimnis-0.0.1.dist-info/LICENSE
fast_string_geheimnis-0.0.1.dist-info/METADATA
fast_string_geheimnis-0.0.1.dist-info/WHEEL
fast_string_geheimnis-0.0.1.dist-info/top_level.txt
fast_string_geheimnis-0.0.1.dist-info/RECORD
